watsonx_minutes/__init__.py
watsonx_minutes/generate_todos.py
watsonx_minutes/ingest.py
watsonx_minutes/prompt.py
watsonx_minutes/wx_client.py
watsonx_minutes-0.4.3.dist-info/METADATA
watsonx_minutes-0.4.3.dist-info/WHEEL
watsonx_minutes-0.4.3.dist-info/entry_points.txt
watsonx_minutes-0.4.3.dist-info/top_level.txt
watsonx_minutes-0.4.3.dist-info/RECORD
