Metadata-Version: 2.4
Name: watsonx-minutes
Version: 0.4.3
Summary: Summarize meeting minutes with watsonx.ai and generate TODOs in a fixed format.
Author-email: Melvin Tah Kok Wai <Melvin.Tah@ibm.com>
License: MIT
Keywords: watsonx.ai,meeting,todo,summarization
Classifier: Programming Language :: Python :: 3
Classifier: License :: OSI Approved :: MIT License
Classifier: Operating System :: OS Independent
Requires-Python: >=3.10
Requires-Dist: ibm-watsonx-ai>=1.3.0
Requires-Dist: striprtf>=0.0.26
Requires-Dist: rich>=13.7.0
Requires-Dist: pypdf>=3.9.0
Requires-Dist: python-docx>=1.1.2
Requires-Dist: beautifulsoup4>=4.12.3
Requires-Dist: python-pptx>=0.6.23
